im2pdf.py
im2pdf-0.1.1.data/scripts/im2pdf
im2pdf-0.1.1.dist-info/METADATA
im2pdf-0.1.1.dist-info/RECORD
im2pdf-0.1.1.dist-info/WHEEL
im2pdf-0.1.1.dist-info/top_level.txt
