Metadata-Version: 1.1
Name: im2pdf
Version: 0.1.1
Summary: Tool to convert image to pdf and unite them.
Home-page: https://github.com/tkmru/im2pdf
Author: @tkmru
Author-email: i.am.tkmru@gmail.com
License: MIT License
Keywords: pdf,jpeg
Platform: UNKNOWN
Classifier: Programming Language :: Python
Classifier: Programming Language :: Python :: 2
Classifier: Programming Language :: Python :: 3
Classifier: Operating System :: OS Independent
Classifier: License :: OSI Approved :: MIT License
